{
    "leads": [
        {"id": 1, "name": "Bruce Wayne", "phoneNumber": "11988887777"},
        {"id": 2, "name": "Tony Stark", "phoneNumber": "41986761256"},
        {"id": 3, "name": "Irmão do Jorel", "phoneNumber": "41999778866"},
        {"id": 4, "name": "Pinguim Oswaldo", "phoneNumber": "41984887522"}
    ],
    "services": [
		{ "id": 1, "service": "Seguro de vida", "icon": "seguro_vida.png" },
		{ "id": 2, "service": "Seguro residencial", "icon": "seguro_residencial.png" },
		{ "id": 3, "service": "Seguro auto", "icon": "seguro_auto.png" }
	]
}